fabdb_sdk/__init__.py
fabdb_sdk/config.py
fabdb_sdk/enums/__init__.py
fabdb_sdk/enums/expansion_set_enum.py
fabdb_sdk/enums/hero_class_enum.py
fabdb_sdk/enums/rarity_enum.py
fabdb_sdk/exceptions/__init__.py
fabdb_sdk/exceptions/not_found_exception.py
fabdb_sdk/helpers/__init__.py
fabdb_sdk/helpers/api_client.py
fabdb_sdk/helpers/enum_helper.py
fabdb_sdk/models/card.py
fabdb_sdk/repositories/__init__.py
fabdb_sdk/repositories/card_repository.py
fabdb_sdk-0.1.0.dist-info/WHEEL
fabdb_sdk-0.1.0.dist-info/METADATA
fabdb_sdk-0.1.0.dist-info/RECORD
