Metadata-Version: 2.1
Name: fabdb-sdk
Version: 0.1.0
Summary: 
Author: Rubem Mota
Author-email: rubemmota89@gmail.com
Requires-Python: >=3.7,<4.0
Classifier: Programming Language :: Python :: 3
Classifier: Programming Language :: Python :: 3.7
Classifier: Programming Language :: Python :: 3.8
Classifier: Programming Language :: Python :: 3.9
Requires-Dist: requests (>=2.26.0,<3.0.0)
